lec3/ex3/ex3-2/stopwatch.v
`timescale 1ns/1ns

`define IDLE  2'b00
`define COUNT 2'b01
`define LAP   2'b10
`define STOP  2'b11

module stopwatch (clk, sw1, sw2, sw3, dsp);
	input        clk, sw1, sw2, sw3;
	output [7:0] dsp;

	reg    [7:0] cnt, dsp;
	reg    [1:0] state, next_state;
	reg          ci, ld, rst;

	always@(sw1 or sw2 or sw3 or state) begin
		case (state)
		/* 以下を記述 */
			`IDLE : begin
				if(sw1 == 1'b1 && sw2 == 1'b0 && sw3 == 1'b0) begin
					next_state <= `COUNT;
				end
			end


			`COUNT : begin
				if(sw1 == 1'b0 && sw2 == 1'b1 && sw3 == 1'b0) begin
					next_state <= `STOP;
				end else if(sw1 == 1'b0 && sw2 == 1'b0 && sw3 == 1'b1) begin
					next_state <= `LAP;
				end
			end

			`LAP : begin
				if(sw1 == 1'b0 && sw2 == 1'b1 && sw3 == 1'b0) begin
					next_state <= `STOP;
				end else if(sw1 == 1'b1 && sw2 == 1'b0 && sw3 == 1'b0) begin
					next_state <= `COUNT;
				end
			end

			`STOP : begin
				if(sw1 == 1'b1 && sw2 == 1'b0 && sw3 == 1'b0) begin
					next_state <= `COUNT;
				end else if(sw1 == 1'b0 && sw2 == 1'b0 && sw3 == 1'b1) begin
					next_state <= `IDLE;
				end
			end

			default : begin
				next_state <= `IDLE;
			end

		/* ここまで */
		endcase
	end

	always@(posedge clk) begin
		state <= next_state;
	end

	always@(state) begin
		case(state)
		/* 以下を記述 */
		`IDLE : begin
			rst <= 1'b0;
			ci <= 1'b0;
			ld <= 1'b0;
		end

		`COUNT : begin
			rst <= 1'b1;
			ci <= 1'b1;
			ld <= 1'b1;
		end

		`LAP : begin
			rst <= 1'b1;
			ci <= 1'b1;
			ld <= 1'b0;
		end

		`STOP : begin
			rst <= 1'b1;
			ci <= 1'b0;
			ld <= 1'b1;
		end

		default : begin
			rst <= 1'b0;
			ci <= 1'b0;
			ld <= 1'b0;
		end

		/* ここまで */
		endcase
	end

	/* 以下を記述 */
	always@(posedge clk) begin
		if(rst == 1'b0) begin
			cnt <= 8'b00000000;
		end else begin
			cnt <= cnt + ci;
		end
	end

	always@(posedge clk) begin
		if(rst == 1'b0) begin
			dsp <= 8'b00000000;
		end else if(ld == 1'b1) begin
			dsp <= cnt;
		end
	end

	/* ここまで */

endmodule

lec3/ans3/ex3-2/test_stopwatch.v
`timescale 1ns/1ns

module test_stopwatch(); 
	reg        clk, sw1, sw2, sw3;
	wire [7:0] dsp;
	
	stopwatch u0(.clk(clk), .sw1(sw1), .sw2(sw2), .sw3(sw3), .dsp(dsp));
	
	initial begin
		$dumpfile( "stopwatch.vcd" );
		$dumpvars( 0, test_stopwatch );
	end
	
	initial begin
		clk = 1'b0;
		forever #5 clk = ~clk;
	end
	
	initial begin
		$monitor( $time,, "clk=%b sw1=%b sw2=%b sw3=%b next_st=%b st=%b cnt=%d dsp=%d",
		clk, sw1, sw2, sw3, u0.next_state, u0.state, u0.cnt, dsp );
	end
	
	initial begin
		sw1 = 1'b0;
		sw2 = 1'b0;
		sw3 = 1'b0;
		#10
		sw1 = 1'b1;
		#20
		sw1 = 1'b0;
		#50
		sw3 = 1'b1;
		#20
		sw3 = 1'b0;
		#20
		sw1 = 1'b1;
		#20
		sw1 = 1'b0;
		#30
		sw3 = 1'b1;
		#20
		sw3 = 1'b0;
		#40
		sw2 = 1'b1;
		#20
		sw2 = 1'b0;
		#20
		sw1 = 1'b1;
		#20
		sw1 = 1'b0;
		#50
		sw2 = 1'b1;
		#20
		sw2 = 1'b0;
		#20
		sw3 = 1'b1;
		#20
		sw3 = 1'b0;
		#20
		$finish();
	end
	
endmodule

lec3/ex3/ex3-2/stopwatch.vcd
$date
	Mon Jul  1 13:06:12 2019
$end
$version
	Icarus Verilog
$end
$timescale
	1ns
$end
$scope module test_stopwatch $end
$var wire 8 ! dsp [7:0] $end
$var reg 1 " clk $end
$var reg 1 # sw1 $end
$var reg 1 $ sw2 $end
$var reg 1 % sw3 $end
$scope module u0 $end
$var wire 1 & clk $end
$var wire 1 ' sw1 $end
$var wire 1 ( sw2 $end
$var wire 1 ) sw3 $end
$var reg 1 * ci $end
$var reg 8 + cnt [7:0] $end
$var reg 8 , dsp [7:0] $end
$var reg 1 - ld $end
$var reg 2 . next_state [1:0] $end
$var reg 1 / rst $end
$var reg 2 0 state [1:0] $end
$upscope $end
$upscope $end
$enddefinitions $end
#0
$dumpvars
bx 0
x/
b0 .
x-
bx ,
bx +
x*
0)
0(
0'
0&
0%
0$
0#
0"
bx !
$end
#5
0-
0*
0/
b0 0
1"
1&
#10
b1 .
0"
0&
1#
1'
#15
1-
1*
1/
b0 ,
b0 !
b0 +
b1 0
1"
1&
#20
0"
0&
#25
b1 +
1"
1&
#30
0"
0&
0#
0'
#35
b1 ,
b1 !
b10 +
1"
1&
#40
0"
0&
#45
b11 +
b10 ,
b10 !
1"
1&
#50
0"
0&
#55
b11 ,
b11 !
b100 +
1"
1&
#60
0"
0&
#65
b101 +
b100 ,
b100 !
1"
1&
#70
0"
0&
#75
b101 ,
b101 !
b110 +
1"
1&
#80
b10 .
0"
0&
1%
1)
#85
0-
b10 0
b111 +
b110 ,
b110 !
1"
1&
#90
0"
0&
#95
b1000 +
1"
1&
#100
0"
0&
0%
0)
#105
b1001 +
1"
1&
#110
0"
0&
#115
b1010 +
1"
1&
#120
b1 .
0"
0&
1#
1'
#125
1-
b1 0
b1011 +
1"
1&
#130
0"
0&
#135
b1011 ,
b1011 !
b1100 +
1"
1&
#140
0"
0&
0#
0'
#145
b1101 +
b1100 ,
b1100 !
1"
1&
#150
0"
0&
#155
b1101 ,
b1101 !
b1110 +
1"
1&
#160
0"
0&
#165
b1111 +
b1110 ,
b1110 !
1"
1&
#170
b10 .
0"
0&
1%
1)
#175
0-
b1111 ,
b1111 !
b10000 +
b10 0
1"
1&
#180
0"
0&
#185
b10001 +
1"
1&
#190
0"
0&
0%
0)
#195
b10010 +
1"
1&
#200
0"
0&
#205
b10011 +
1"
1&
#210
0"
0&
#215
b10100 +
1"
1&
#220
0"
0&
#225
b10101 +
1"
1&
#230
b11 .
0"
0&
1$
1(
#235
1-
0*
b10110 +
b11 0
1"
1&
#240
0"
0&
#245
b10110 ,
b10110 !
1"
1&
#250
0"
0&
0$
0(
#255
1"
1&
#260
0"
0&
#265
1"
1&
#270
b1 .
0"
0&
1#
1'
#275
1*
b1 0
1"
1&
#280
0"
0&
#285
b10111 +
1"
1&
#290
0"
0&
0#
0'
#295
b10111 ,
b10111 !
b11000 +
1"
1&
#300
0"
0&
#305
b11001 +
b11000 ,
b11000 !
1"
1&
#310
0"
0&
#315
b11001 ,
b11001 !
b11010 +
1"
1&
#320
0"
0&
#325
b11011 +
b11010 ,
b11010 !
1"
1&
#330
0"
0&
#335
b11011 ,
b11011 !
b11100 +
1"
1&
#340
b11 .
0"
0&
1$
1(
#345
0*
b11 0
b11101 +
b11100 ,
b11100 !
1"
1&
#350
0"
0&
#355
b11101 ,
b11101 !
1"
1&
#360
0"
0&
0$
0(
#365
1"
1&
#370
0"
0&
#375
1"
1&
#380
b0 .
0"
0&
1%
1)
#385
0-
0/
b0 0
1"
1&
#390
0"
0&
#395
b0 ,
b0 !
b0 +
1"
1&
#400
0"
0&
0%
0)
