lec5/ex5/reg.v
`timescale 1ns/1ns

module regf(clk, we, din, a, dout_a, b, dout_b);
	input        clk, we;
	input  [3:0] din;
	input  [1:0] a, b;
	output [3:0] dout_a, dout_b;
	reg    [3:0] data [0:3];
	always@(posedge clk) begin
		if(we == 1'b1) begin
			data[a] <= din;
		end
	end
	assign dout_a = data[a];
	assign dout_b = data[b];

	initial begin
		data[0] = 4'h0;
		data[1] = 4'h0;
		data[2] = 4'h0;
		data[3] = 4'h0;
	end
	wire   [3:0] r0, r1, r2, r3;
	assign r0 = data[0];
	assign r1 = data[1];
	assign r2 = data[2];
	assign r3 = data[3];
endmodule

module reg8(clk, rst, we, din, dout);
	input        clk, rst, we;
	input  [7:0] din;
	output [7:0] dout;
	reg    [7:0] dout;

	always@(posedge clk) begin
		if(rst == 1'b0) begin
			dout <= 8'b00000000;
		end else if(we == 1'b1) begin
			dout <= din;
		end
	end
endmodule

module reg4(clk, rst, we, din, dout);
	input        clk, rst, we;
	input  [3:0] din;
	output [3:0] dout;
	reg    [3:0] dout;

	always@(posedge clk) begin
		if(rst == 1'b0) begin
			dout <= 4'b0000;
		end else if(we == 1'b1) begin
			dout <= din;
		end
	end
endmodule

module reg2(clk, rst, we, din, dout);
	input        clk, rst, we;
	input  [1:0] din;
	output [1:0] dout;
	reg    [1:0] dout;

	always@(posedge clk) begin
		if(rst == 1'b0) begin
			dout <= 2'b00;
		end else if(we == 1'b1) begin
			dout <= din;
		end
	end
endmodule

lec5/ex5/ex5-1/csg.v
`timescale 1ns/1ns

`define LDI  4'b0000
`define MOV  4'b0001
`define ADD  4'b0010
`define SUB  4'b0011
`define LD   4'b0100
`define ST   4'b0101
`define JMP  4'b0110

/* 課題(2)
	制御信号alu_selを追加
	ADDとSUBの制御を追加
	LDIとMOVの制御を変更
 */
/* 課題(3)
	制御信号pr_selを追加
	JMPの制御を追加
	命令読み出し(時刻0)の制御を変更
 */

module csg(
	iru, sr,
	gr_sel, br_sel, dr_sel,
	alu_sel,
	ir_we, pr_we, gr_we,
	dm_re, dm_we,
	pr_sel
);
	input   [3:0] iru;
	input   [1:0] sr;
	output        gr_sel, br_sel, dr_sel;
	output[1:0]				alu_sel;
	output        ir_we, pr_we, gr_we;
	output        dm_re, dm_we;
	output				pr_sel;
	reg           gr_sel, br_sel, dr_sel;
	reg           ir_we, pr_we, gr_we;
	reg           dm_re, dm_we;
	reg[1:0]			alu_sel;
	reg						pr_sel;

	always@(iru or sr) begin
		pr_sel <= 1'bx;
		gr_sel <= 1'bx;
		br_sel <= 1'bx;
		dr_sel <= 1'bx;
		alu_sel <= 2'bxx;
		ir_we  <= 1'b0;
		pr_we  <= 1'b0;
		gr_we  <= 1'b0;
		dm_re  <= 1'b0;
		dm_we  <= 1'b0;
		case(sr)
			2'b00: begin
				ir_we <= 1'b1;
				pr_we <= 1'b1;
				pr_sel = 1'b1;
			end

			2'b01: begin
				case(iru)
					`LDI: begin
						br_sel <= 1'b0;
					end
					`MOV, `LD: begin
						br_sel <= 1'b1;
					end
					`ST: begin
						gr_sel <= 1'b1;
						br_sel <= 1'b1;
					end
					`ADD: begin
						gr_sel <= 1'b1;
						br_sel <= 1'b1;
					end
					`SUB: begin
						gr_sel <= 1'b1;
						br_sel <= 1'b1;
					end
					`JMP:	begin
						pr_sel <= 1'b0;
						pr_we <= 1'b1;
					end
				endcase
			end
			2'b10: begin
				case(iru)
					`LDI, `MOV: begin
						dr_sel <= 1'b1;
						alu_sel <= 2'b01;
					end
					`LD: begin
						dm_re <= 1'b1;
						dr_sel <= 1'b0;
					end
					`ST: begin
						dm_we <= 1'b1;
					end
					`ADD: begin
						alu_sel <= 2'b10;
						dr_sel <= 1'b1;
					end
					`SUB: begin
					 	alu_sel <= 2'b11;
						dr_sel <= 1'b1;
					end


				endcase
			end
			2'b11: begin
				case(iru)
					`LDI: begin
						gr_sel <= 1'b0;
						gr_we <= 1'b1;
					end
					`MOV, `LD, `ADD, `SUB: begin
						gr_sel <= 1'b1;
						gr_we <= 1'b1;
					end
				endcase
			end
		endcase
	end
endmodule

lec5/ex5/alu.v
`timescale 1ns/1ns

module alu(a, b, sel, y);
	input  [3:0] a, b;
	input  [1:0] sel;
	output [3:0] y;
	reg    [3:0] y;

	always@(a or b or sel) begin
		case(sel)
		/* 以下を記述*/
		4'b0000: y <= 8'h05;
		4'b0001: y <= 8'h14;
		4'b0010: y <= 8'h02;
		4'b0011: y <= 8'h54;
		4'b0100: y <= 8'h48;
		4'b0101: y <= 8'h1e;
		4'b0110: y <= 8'h24;
		4'b0111: y <= 8'h38;
		4'b1000: y <= 8'hxx;
		4'b1001: y <= 8'hxx;
		4'b1010: y <= 8'hxx;
		4'b1011: y <= 8'hxx;
		4'b1100: y <= 8'hxx;
		4'b1101: y <= 8'hxx;
		4'b1110: y <= 8'hxx;
		4'b1111: y <= 8'hxx;
		default: y <= 8'hxx;
		/* ここまで */
		default: y <= 4'bxxxx;
		endcase
	end
endmodule

lec6/ex6/ram.v
`timescale 1ns/1ns

module ram(clk, re, we, adrs, din, dout);
	input        clk, re, we;
	input  [3:0] adrs, din;
	output [3:0] dout;
	reg    [3:0] data [0:15];
	always@(posedge clk) begin
		if(we == 1'b1) begin
			data[adrs] <= din;
		end
	end
	assign dout = (re == 1'b1) ? data[adrs] : 4'bxxxx;
	
	initial begin
		data[0] = 4'h0;
		data[1] = 4'h0;
		data[2] = 4'h0;
		data[3] = 4'h0;
		data[4] = 4'h0;
		data[5] = 4'h0;
		data[6] = 4'h0;
		data[7] = 4'h0;
		data[8] = 4'h0;
		data[9] = 4'h0;
		data[10] = 4'h0;
		data[11] = 4'h0;
		data[12] = 4'h0;
		data[13] = 4'h0;
		data[14] = 4'h0;
		data[15] = 4'h0;
	end
	wire [3:0] m0, m1, m2, m3;
	assign m0 = data[0];
	assign m1 = data[1];
	assign m2 = data[2];
	assign m3 = data[3];
endmodule

lec5/ex5/ex5-1/rom.v
`timescale 1ns/1ns

module rom(adrs, dout);
	input  [3:0] adrs;
	output [7:0] dout;
	reg    [7:0] dout;

	always@(adrs) begin
		case(adrs)
			/* 以下にプログラムを記述 */
			4'b0000: dout <= 8'h05;
			4'b0001: dout <= 8'h14;
			4'b0010: dout <= 8'h02;
			4'b0011: dout <= 8'h54;
			4'b0100: dout <= 8'h48;
			4'b0101: dout <= 8'h1e;
			4'b0110: dout <= 8'hxx;
			4'b0111: dout <= 8'hxx;
			4'b1000: dout <= 8'hxx;
			4'b1001: dout <= 8'hxx;
			4'b1010: dout <= 8'hxx;
			4'b1011: dout <= 8'hxx;
			4'b1100: dout <= 8'hxx;
			4'b1101: dout <= 8'hxx;
			4'b1110: dout <= 8'hxx;
			4'b1111: dout <= 8'hxx;
			default: dout <= 8'hxx;
			/* ここまで */
		endcase
	end
endmodule

lec5/ex5/data_path.v
`timescale 1ns/1ns

/* 課題(2)
	制御信号alu_selを追加
	csgに出力ポートを追加
	aluを追加
	dr_dinに対するマルチプレクサを変更
 */

/* 課題(3)
	制御信号pr_selを追加
	csgに出力ポートを追加
	pr_dinに対するマルチプレクサを追加
 */

module data_path(
	clk, rst
);
	input      clk, rst;
	/*--- instruction fetch ---*/
	wire [3:0] pr_din, pr_dout;
	wire [3:0] im_adrs;
	wire [7:0] im_dout;
	wire [7:0] ir_din, ir_dout;
	/*--- register fetch ---*/
	wire [1:0] gr_a, gr_b;
	wire [3:0] gr_din, gr_dout_a, gr_dout_b;
	wire [3:0] ar_din, ar_dout;
	wire [3:0] br_din, br_dout;
	/*--- execution ---*/
	wire [3:0] dm_adrs, dm_din, dm_dout;
	wire [3:0] dr_din, dr_dout;
	/*--- state register ---*/
	wire [1:0] sr_din, sr_dout;
	/*--- control signal ---*/
	wire       gr_sel, br_sel, dr_sel;
	wire       ir_we, pr_we, gr_we;
	wire       dm_re, dm_we;
	wire[1:0]	 alu_sel;
	wire[3:0]			alu_din1, alu_din2, alu_dout;
	wire				pr_sel;


	/*--- instruction fetch ---*/
	assign pr_din = (pr_sel == 1'b1) ? pr_dout + 4'b0001 : pr_dout;
	reg4 pc(.clk(clk), .rst(rst), .we(pr_we), .din(pr_din), .dout(pr_dout));

	assign im_adrs = pr_dout;
	rom im(.adrs(im_adrs), .dout(im_dout));

	assign ir_din = im_dout;
	reg8 ir(.clk(clk), .rst(rst), .we(ir_we), .din(ir_din), .dout(ir_dout));
	/*--- register fetch ---*/
	assign gr_a = (gr_sel == 1'b1) ? ir_dout[3:2] : 2'b00;
	assign gr_b = ir_dout[1:0];
	assign gr_din = dr_dout;
	regf gr(.clk(clk), .we(gr_we), .din(gr_din),
			.a(gr_a), .dout_a(gr_dout_a), .b(gr_b), .dout_b(gr_dout_b));

	assign ar_din = gr_dout_a;
	reg4 ar(.clk(clk), .rst(1'b1), .we(1'b1), .din(ar_din), .dout(ar_dout));

	assign br_din = (br_sel == 1'b1) ? gr_dout_b : ir_dout[3:0];
	reg4 br(.clk(clk), .rst(1'b1), .we(1'b1), .din(br_din), .dout(br_dout));
	/*--- execution ---*/
	assign dm_adrs = br_dout;
	assign dm_din = ar_dout;
	ram dm(.clk(clk), .re(dm_re), .we(dm_we),
		.adrs(dm_adrs), .din(dm_din), .dout(dm_dout));

	/*kadai2*/
	alu alu(.a(alu_din1), .b(alu_din2), .sel(alu_sel), .(alu_dout));

	assign dr_din = (dr_sel == 1'b1) ? alu_dout : dm_dout;

	reg4 dr(.clk(clk), .rst(1'b1), .we(1'b1), .din(dr_din), .dout(dr_dout));
	/*--- state register ---*/
	assign sr_din = sr_dout + 2'b01;
	reg2 sc(.clk(clk), .rst(rst), .we(1'b1), .din(sr_din), .dout(sr_dout));

	/*--- control signal ---*/
	csg csg(
		.iru(ir_dout[7:4]),  .sr(sr_dout),
		.gr_sel(gr_sel), .br_sel(br_sel), .dr_sel(dr_sel),
		.alu_sel(alu_sel),
		.ir_we(ir_we), .pr_we(pr_we), .gr_we(gr_we),
		.dm_re(dm_re), .dm_we(dm_we),
		.pr_sel(pr_sel));

	
	/*kadai3*/
	assign pr_din = (pr_sel == 1'b1) ? pr_din : ir_dout;
	reg4 jmp(.clk(clk), .rst(1'b1), .we(1'b1), .din(dr_din), .dout(dr_dout));



endmodule

lec5/ex5/ex5-1/test.v
`timescale 1ns/1ns

module test();
	reg clk, rst;

	data_path dp(.clk(clk), .rst(rst));

	initial begin
		$dumpfile("cpu.vcd");
		$dumpvars(0, test);
	end
	initial begin
		clk = 1'b0;
		forever #5 clk = ~clk;
	end
	initial begin
		$display($time, " SR PR IR AR BR DR: R0 R1 R2 R3: M0 M1 M2 M3");
		rst = 1'b0;
		#8
		rst = 1'b1;
		#350
		$finish();
	end
	initial begin
		$monitor($time,," %h  %h %h  %h  %h  %h:  %h  %h  %h  %h:  %h  %h  %h  %h",
		dp.sr_dout, dp.pr_dout, dp.ir_dout,
		dp.ar_dout, dp.br_dout, dp.dr_dout, 
		dp.gr.r0, dp.gr.r1, dp.gr.r2, dp.gr.r3,
		dp.dm.m0, dp.dm.m1, dp.dm.m2, dp.dm.m3);
	end
endmodule

lec5/ex5/cpu.vcd
$date
	Mon Jul 15 09:12:28 2019
$end
$version
	Icarus Verilog
$end
$timescale
	1ns
$end
$scope module test $end
$var reg 1 ! clk $end
$var reg 1 " rst $end
$scope module dp $end
$var wire 4 # alu_din1 [3:0] $end
$var wire 4 $ alu_din2 [3:0] $end
$var wire 4 % alu_dout [3:0] $end
$var wire 2 & alu_sel [1:0] $end
$var wire 4 ' ar_din [3:0] $end
$var wire 4 ( ar_dout [3:0] $end
$var wire 4 ) br_din [3:0] $end
$var wire 4 * br_dout [3:0] $end
$var wire 1 + br_sel $end
$var wire 1 , clk $end
$var wire 4 - dm_adrs [3:0] $end
$var wire 4 . dm_din [3:0] $end
$var wire 4 / dm_dout [3:0] $end
$var wire 1 0 dm_re $end
$var wire 1 1 dm_we $end
$var wire 4 2 dr_din [3:0] $end
$var wire 4 3 dr_dout [3:0] $end
$var wire 1 4 dr_sel $end
$var wire 2 5 gr_a [1:0] $end
$var wire 2 6 gr_b [1:0] $end
$var wire 4 7 gr_din [3:0] $end
$var wire 4 8 gr_dout_a [3:0] $end
$var wire 4 9 gr_dout_b [3:0] $end
$var wire 1 : gr_sel $end
$var wire 1 ; gr_we $end
$var wire 4 < im_adrs [3:0] $end
$var wire 8 = im_dout [7:0] $end
$var wire 8 > ir_din [7:0] $end
$var wire 8 ? ir_dout [7:0] $end
$var wire 1 @ ir_we $end
$var wire 4 A pr_din [3:0] $end
$var wire 4 B pr_dout [3:0] $end
$var wire 1 C pr_sel $end
$var wire 1 D pr_we $end
$var wire 1 E rst $end
$var wire 2 F sr_din [1:0] $end
$var wire 2 G sr_dout [1:0] $end
$scope module pc $end
$var wire 1 , clk $end
$var wire 4 H din [3:0] $end
$var wire 1 E rst $end
$var wire 1 D we $end
$var reg 4 I dout [3:0] $end
$upscope $end
$scope module im $end
$var wire 4 J adrs [3:0] $end
$var reg 8 K dout [7:0] $end
$upscope $end
$scope module ir $end
$var wire 1 , clk $end
$var wire 8 L din [7:0] $end
$var wire 1 E rst $end
$var wire 1 @ we $end
$var reg 8 M dout [7:0] $end
$upscope $end
$scope module gr $end
$var wire 2 N a [1:0] $end
$var wire 2 O b [1:0] $end
$var wire 1 , clk $end
$var wire 4 P din [3:0] $end
$var wire 4 Q dout_a [3:0] $end
$var wire 4 R dout_b [3:0] $end
$var wire 4 S r0 [3:0] $end
$var wire 4 T r1 [3:0] $end
$var wire 4 U r2 [3:0] $end
$var wire 4 V r3 [3:0] $end
$var wire 1 ; we $end
$upscope $end
$scope module ar $end
$var wire 1 , clk $end
$var wire 4 W din [3:0] $end
$var wire 1 X rst $end
$var wire 1 Y we $end
$var reg 4 Z dout [3:0] $end
$upscope $end
$scope module br $end
$var wire 1 , clk $end
$var wire 4 [ din [3:0] $end
$var wire 1 \ rst $end
$var wire 1 ] we $end
$var reg 4 ^ dout [3:0] $end
$upscope $end
$scope module dm $end
$var wire 4 _ adrs [3:0] $end
$var wire 1 , clk $end
$var wire 4 ` din [3:0] $end
$var wire 4 a dout [3:0] $end
$var wire 4 b m0 [3:0] $end
$var wire 4 c m1 [3:0] $end
$var wire 4 d m2 [3:0] $end
$var wire 4 e m3 [3:0] $end
$var wire 1 0 re $end
$var wire 1 1 we $end
$upscope $end
$scope module dr $end
$var wire 1 , clk $end
$var wire 4 f din [3:0] $end
$var wire 1 g rst $end
$var wire 1 h we $end
$var reg 4 i dout [3:0] $end
$upscope $end
$scope module sc $end
$var wire 1 , clk $end
$var wire 2 j din [1:0] $end
$var wire 1 E rst $end
$var wire 1 k we $end
$var reg 2 l dout [1:0] $end
$upscope $end
$scope module csg $end
$var wire 4 m iru [3:0] $end
$var wire 2 n sr [1:0] $end
$var reg 2 o alu_sel [1:0] $end
$var reg 1 p br_sel $end
$var reg 1 q dm_re $end
$var reg 1 r dm_we $end
$var reg 1 s dr_sel $end
$var reg 1 t gr_sel $end
$var reg 1 u gr_we $end
$var reg 1 v ir_we $end
$var reg 1 w pr_sel $end
$var reg 1 x pr_we $end
$upscope $end
$scope module alu $end
$var wire 4 y a [3:0] $end
$var wire 4 z b [3:0] $end
$var wire 2 { sel [1:0] $end
$var reg 4 | y [3:0] $end
$upscope $end
$scope module jmp $end
$var wire 1 , clk $end
$var wire 4 } din [3:0] $end
$var wire 1 ~ rst $end
$var wire 1 !" we $end
$var reg 4 "" dout [3:0] $end
$upscope $end
$upscope $end
$upscope $end
$enddefinitions $end
#0
$dumpvars
bx ""
1!"
1~
bx }
bx |
bx {
bx z
bx y
0x
xw
0v
0u
xt
xs
0r
0q
xp
bx o
bx n
bx m
bx l
1k
bx j
bx i
1h
1g
bx f
b0 e
b0 d
b0 c
b0 b
bx a
bx `
bx _
bx ^
1]
1\
bx [
bx Z
1Y
1X
bx W
b0 V
b0 U
b0 T
b0 S
bx R
bx Q
bx P
bx O
bx N
bx M
bx L
bx K
bx J
bx I
bx H
bx G
bx F
0E
0D
xC
bx B
bx A
0@
bx ?
bx >
bx =
bx <
0;
x:
bx 9
bx 8
bx 7
bx 6
bx 5
x4
bx 3
bx 2
01
00
bx /
bx .
bx -
0,
x+
bx *
bx )
bx (
bx '
bx &
bx %
bx $
bx #
0"
0!
$end
#5
b101 K
b101 =
b101 >
b101 L
1x
1D
1v
1@
b0 )
b0 [
b0 8
b0 Q
b0 '
b0 W
b0 5
b0 N
b0 m
b0 9
b0 R
b0 6
b0 O
xw
xC
b0 I
b0 B
b0 <
b0 J
b0 M
b0 ?
b0 l
b1 F
b1 j
b0 G
b0 n
1!
1,
#8
1"
1E
#10
0!
0,
#15
0p
0+
0x
0D
0v
0@
bx K
bx =
bx >
bx L
b101 )
b101 [
bx 8
bx Q
bx '
bx W
b0x 5
b0x N
b1 6
b1 O
b1 l
b10 F
b10 j
b1 G
b1 n
b0 ^
b0 *
b0 $
b0 z
b0 -
b0 _
b0 Z
b0 (
b0 #
b0 y
b0 .
b0 `
b101 M
b101 ?
bx I
bx B
bx <
bx J
1!
1,
#20
0!
0,
#25
b100 2
b100 f
b100 }
b100 |
b100 %
b0x0x )
b0x0x [
b1 o
b1 &
b1 {
1s
14
xp
x+
bx Z
bx (
bx #
bx y
bx .
bx `
b101 ^
b101 *
b101 $
b101 z
b101 -
b101 _
b10 l
b11 F
b11 j
b10 G
b10 n
1!
1,
#30
0!
0,
#35
bx |
bx %
b0 8
b0 Q
b0 '
b0 W
b0 5
b0 N
bx 2
bx f
bx }
1u
1;
0t
0:
bx o
bx &
bx {
xs
x4
b100 ""
b100 7
b100 P
b100 3
b11 l
b0 F
b0 j
b11 G
b11 n
b100 i
b0x0x ^
b0x0x *
b0x0x $
b0x0x z
b0x0x -
b0x0x _
1!
1,
#40
0!
0,
#45
b0x 5
b0x N
1x
1D
1v
1@
0u
0;
xt
x:
xw
xC
b100 S
bx 8
bx Q
bx '
bx W
b0 Z
b0 (
b0 #
b0 y
b0 .
b0 `
bx i
b0 l
b1 F
b1 j
b0 G
b0 n
bx ""
bx 7
bx P
bx 3
1!
1,
#50
0!
0,
#55
0x
0D
0v
0@
bx )
bx [
bx 5
bx N
bx m
bx 9
bx R
bx 6
bx O
b1 l
b10 F
b10 j
b1 G
b1 n
bx Z
bx (
bx #
bx y
bx .
bx `
bx M
bx ?
1!
1,
#60
0!
0,
#65
bx ^
bx *
bx $
bx z
bx -
bx _
b10 l
b11 F
b11 j
b10 G
b10 n
1!
1,
#70
0!
0,
#75
b11 l
b0 F
b0 j
b11 G
b11 n
1!
1,
#80
0!
0,
#85
1x
1D
1v
1@
xw
xC
b0 l
b1 F
b1 j
b0 G
b0 n
1!
1,
#90
0!
0,
#95
0x
0D
0v
0@
b1 l
b10 F
b10 j
b1 G
b1 n
1!
1,
#100
0!
0,
#105
b10 l
b11 F
b11 j
b10 G
b10 n
1!
1,
#110
0!
0,
#115
b11 l
b0 F
b0 j
b11 G
b11 n
1!
1,
#120
0!
0,
#125
1x
1D
1v
1@
xw
xC
b0 l
b1 F
b1 j
b0 G
b0 n
1!
1,
#130
0!
0,
#135
0x
0D
0v
0@
b1 l
b10 F
b10 j
b1 G
b1 n
1!
1,
#140
0!
0,
#145
b10 l
b11 F
b11 j
b10 G
b10 n
1!
1,
#150
0!
0,
#155
b11 l
b0 F
b0 j
b11 G
b11 n
1!
1,
#160
0!
0,
#165
1x
1D
1v
1@
xw
xC
b0 l
b1 F
b1 j
b0 G
b0 n
1!
1,
#170
0!
0,
#175
0x
0D
0v
0@
b1 l
b10 F
b10 j
b1 G
b1 n
1!
1,
#180
0!
0,
#185
b10 l
b11 F
b11 j
b10 G
b10 n
1!
1,
#190
0!
0,
#195
b11 l
b0 F
b0 j
b11 G
b11 n
1!
1,
#200
0!
0,
#205
1x
1D
1v
1@
xw
xC
b0 l
b1 F
b1 j
b0 G
b0 n
1!
1,
#210
0!
0,
#215
0x
0D
0v
0@
b1 l
b10 F
b10 j
b1 G
b1 n
1!
1,
#220
0!
0,
#225
b10 l
b11 F
b11 j
b10 G
b10 n
1!
1,
#230
0!
0,
#235
b11 l
b0 F
b0 j
b11 G
b11 n
1!
1,
#240
0!
0,
#245
1x
1D
1v
1@
xw
xC
b0 l
b1 F
b1 j
b0 G
b0 n
1!
1,
#250
0!
0,
#255
0x
0D
0v
0@
b1 l
b10 F
b10 j
b1 G
b1 n
1!
1,
#260
0!
0,
#265
b10 l
b11 F
b11 j
b10 G
b10 n
1!
1,
#270
0!
0,
#275
b11 l
b0 F
b0 j
b11 G
b11 n
1!
1,
#280
0!
0,
#285
1x
1D
1v
1@
xw
xC
b0 l
b1 F
b1 j
b0 G
b0 n
1!
1,
#290
0!
0,
#295
0x
0D
0v
0@
b1 l
b10 F
b10 j
b1 G
b1 n
1!
1,
#300
0!
0,
#305
b10 l
b11 F
b11 j
b10 G
b10 n
1!
1,
#310
0!
0,
#315
b11 l
b0 F
b0 j
b11 G
b11 n
1!
1,
#320
0!
0,
#325
1x
1D
1v
1@
xw
xC
b0 l
b1 F
b1 j
b0 G
b0 n
1!
1,
#330
0!
0,
#335
0x
0D
0v
0@
b1 l
b10 F
b10 j
b1 G
b1 n
1!
1,
#340
0!
0,
#345
b10 l
b11 F
b11 j
b10 G
b10 n
1!
1,
#350
0!
0,
#355
b11 l
b0 F
b0 j
b11 G
b11 n
1!
1,
