lec4/ex4/ex4-1/mul.v
`timescale 1ns/1ns

module mul(clk, ld, a, b, y);
	input        clk; /* クロック */
	input        ld;  /* ロード */
	input  [3:0] a;   /* 被乗数 */
	input  [3:0] b;   /* 乗数 */
	output [7:0] y;   /* 積 */

	reg [7:0] ra; /* 被乗数レジスタ */
	reg [3:0] rb; /* 乗数レジスタ */
	reg [7:0] ry; /* 積レジスタ */

	/* 以下を記述 */
/*

		always@(posedge clk) begin
			if(ld == 1'b1) begin
				ra <= a;
			end else begin
				ra <= {a[6:0], 1'b0};
			end
		end

		always@(posedge clk) begin
			if(ld == 1'b1) begin
				rb <= b;
			end else begin
				rb <= {1'b0, b[3:1]};
			end
		end

		always@(posedge clk) begin
			if(rb[0] == 1'b1) begin
				ra <= a;
			end
			ry <= y + ra;
		end
*/
/*以下解答*/

		always@(posedge clk) begin
			if(ld == 1'b1) begin
				ra <= {4'b0000, a};
			end else begin
				ra <= {ra[6:0], 1'b0};
			end
		end

		always@(posedge clk) begin
			if(ld == 1'b1) begin
				rb <= b;
			end else begin
				rb <= {1'b0, rb[3:1]};
			end
		end

		always@(posedge clk) begin
			if(ld == 1'b1) begin
				ry <= 8'b00000000;
			end else if(rb[0] == 1'b1) begin
				ry <= ry + ra;
			end
		end



	/* ここまで */

	assign y = ry;
endmodule

lec4/ex4/ex4-1/test_mul.v
`timescale 1ns/1ns

module test_mul();
	reg        clk, ld;
	reg  [3:0] a, b;
	wire [7:0] y;

	mul u0(.clk(clk), .ld(ld), .a(a), .b(b), .y(y));

	initial begin
		$dumpfile("mul.vcd");
		$dumpvars(0, test_mul);
	end

	initial begin
		$monitor($time,, "%b %b %b", u0.ra, u0.rb, u0.ry);
	end

	initial begin
		clk = 1'b0;
		forever #10 clk = ~clk;
	end

	initial begin
		/* 以下を記述 */
		ld = 1'b0;
		a = 4'b1101;
		b = 4'b1011;
		#10
		ld = 1'b1;	
		a = 4'b1101;
		b = 4'b1011;
		#20
		ld = 1'b0;
		a = 4'b1101;
		b = 4'b1011;
		#30
		ld = 1'b0;
		a = 4'b1101;
		b = 4'b1011;
		#40
		ld = 1'b1;	
		a = 4'b1101;
		b = 4'b1011;
		#50
		ld = 1'b0;
		a = 4'b1101;
		b = 4'b1011;
		#60


	




		/* ここまで */
		$finish();
	end

endmodule

lec4/ex4/ex4-1/mul.vcd
$date
	Mon Jul  8 13:31:35 2019
$end
$version
	Icarus Verilog
$end
$timescale
	1ns
$end
$scope module test_mul $end
$var wire 8 ! y [7:0] $end
$var reg 4 " a [3:0] $end
$var reg 4 # b [3:0] $end
$var reg 1 $ clk $end
$var reg 1 % ld $end
$scope module u0 $end
$var wire 4 & a [3:0] $end
$var wire 4 ' b [3:0] $end
$var wire 1 ( clk $end
$var wire 1 ) ld $end
$var wire 8 * y [7:0] $end
$var reg 8 + ra [7:0] $end
$var reg 4 , rb [3:0] $end
$var reg 8 - ry [7:0] $end
$upscope $end
$upscope $end
$enddefinitions $end
#0
$dumpvars
bx -
bx ,
bx +
bx *
0)
0(
b1011 '
b1101 &
0%
0$
b1011 #
b1101 "
bx !
$end
#10
b1101 +
b1011 ,
b0 -
b0 !
b0 *
1%
1)
1$
1(
#20
0$
0(
#30
b1101 -
b1101 !
b1101 *
b101 ,
b11010 +
1$
1(
0%
0)
#40
0$
0(
#50
b110100 +
b10 ,
b100111 -
b100111 !
b100111 *
1$
1(
#60
0$
0(
#70
b1 ,
b1101000 +
1$
1(
#80
0$
0(
#90
b11010000 +
b0 ,
b10001111 -
b10001111 !
b10001111 *
1$
1(
#100
0$
0(
1%
1)
#110
b0 -
b0 !
b0 *
b1011 ,
b1101 +
1$
1(
#120
0$
0(
#130
1$
1(
#140
0$
0(
#150
b1101 -
b1101 !
b1101 *
b101 ,
b11010 +
1$
1(
0%
0)
#160
0$
0(
#170
b110100 +
b10 ,
b100111 -
b100111 !
b100111 *
1$
1(
#180
0$
0(
#190
b1 ,
b1101000 +
1$
1(
#200
0$
0(
#210
b11010000 +
b0 ,
b10001111 -
b10001111 !
b10001111 *
1$
1(
